rdf_engine/__init__.py
rdf_engine/canon.py
rdf_engine/cli.py
rdf_engine/conversions.py
rdf_engine/data.py
rdf_engine/db.py
rdf_engine/engine.py
rdf_engine/program.py
rdf_engine/rules.py
rdf_engine-231.dist-info/METADATA
rdf_engine-231.dist-info/WHEEL
rdf_engine-231.dist-info/entry_points.txt
rdf_engine-231.dist-info/RECORD
