Metadata-Version: 2.4
Name: rdf-engine
Version: 231
Summary: A rules engine for RDF data
Author-email: Majid alDosari <majid.aldosari@pnnl.gov>, Majid alDosari <majidaldosari-github@yahoo.com>
Requires-Python: >=3.11
Requires-Dist: loguru
Requires-Dist: pyoxigraph>=0.5.0
Requires-Dist: rdflib
Provides-Extra: cli
Requires-Dist: pyyaml; extra == 'cli'
